ratelimitingfilter/__init__.py
ratelimitingfilter/ratelimitingfilter.py
ratelimitingfilter-1.4.dist-info/LICENSE.txt
ratelimitingfilter-1.4.dist-info/METADATA
ratelimitingfilter-1.4.dist-info/WHEEL
ratelimitingfilter-1.4.dist-info/top_level.txt
ratelimitingfilter-1.4.dist-info/RECORD
